{
  "game_0000.npz": [
    145,
    3679
  ],
  "game_0001.npz": [
    62,
    2513
  ],
  "game_0002.npz": [
    112,
    3174
  ],
  "game_0003.npz": [
    138,
    3574
  ],
  "game_0004.npz": [
    111,
    3227
  ],
  "game_0005.npz": [
    62,
    2560
  ],
  "game_0006.npz": [
    138,
    3629
  ],
  "game_0007.npz": [
    64,
    2603
  ],
  "game_0008.npz": [
    135,
    3565
  ],
  "game_0009.npz": [
    64,
    2593
  ],
  "game_0010.npz": [
    76,
    2702
  ],
  "game_0011.npz": [
    62,
    2555
  ],
  "game_0012.npz": [
    142,
    3627
  ],
  "game_0013.npz": [
    250,
    5052
  ],
  "game_0014.npz": [
    62,
    2577
  ],
  "game_0015.npz": [
    62,
    2559
  ],
  "game_0016.npz": [
    140,
    3565
  ],
  "game_0017.npz": [
    155,
    3755
  ],
  "game_0018.npz": [
    113,
    3300
  ],
  "game_0019.npz": [
    151,
    3833
  ],
  "game_0020.npz": [
    72,
    2678
  ],
  "game_0021.npz": [
    63,
    2569
  ],
  "game_0022.npz": [
    62,
    2571
  ],
  "game_0023.npz": [
    120,
    3338
  ],
  "game_0024.npz": [
    123,
    3347
  ],
  "game_0025.npz": [
    128,
    3456
  ],
  "game_0026.npz": [
    62,
    2540
  ],
  "game_0027.npz": [
    64,
    2602
  ],
  "game_0028.npz": [
    62,
    2558
  ],
  "game_0029.npz": [
    162,
    3835
  ],
  "game_0030.npz": [
    63,
    2600
  ],
  "game_0031.npz": [
    113,
    3301
  ],
  "game_0032.npz": [
    250,
    5041
  ],
  "game_0033.npz": [
    62,
    2604
  ],
  "game_0034.npz": [
    140,
    3576
  ],
  "game_0035.npz": [
    62,
    2535
  ],
  "game_0036.npz": [
    62,
    2604
  ],
  "game_0037.npz": [
    147,
    3781
  ],
  "game_0038.npz": [
    138,
    3650
  ],
  "game_0039.npz": [
    142,
    3645
  ],
  "game_0040.npz": [
    154,
    3801
  ],
  "game_0041.npz": [
    117,
    3318
  ],
  "game_0042.npz": [
    122,
    3335
  ],
  "game_0043.npz": [
    64,
    2565
  ],
  "game_0044.npz": [
    153,
    3755
  ],
  "game_0045.npz": [
    106,
    3190
  ],
  "game_0046.npz": [
    138,
    3637
  ],
  "game_0047.npz": [
    63,
    2563
  ],
  "game_0048.npz": [
    63,
    2590
  ],
  "game_0049.npz": [
    64,
    2573
  ],
  "game_0050.npz": [
    62,
    2513
  ],
  "game_0051.npz": [
    113,
    3217
  ],
  "game_0052.npz": [
    74,
    2731
  ],
  "game_0053.npz": [
    104,
    3132
  ],
  "game_0054.npz": [
    120,
    3394
  ],
  "game_0055.npz": [
    123,
    3436
  ],
  "game_0056.npz": [
    101,
    3123
  ],
  "game_0057.npz": [
    94,
    2966
  ],
  "game_0058.npz": [
    117,
    3363
  ],
  "game_0059.npz": [
    62,
    2573
  ],
  "game_0060.npz": [
    128,
    3440
  ],
  "game_0061.npz": [
    63,
    2546
  ],
  "game_0062.npz": [
    62,
    2581
  ],
  "game_0063.npz": [
    130,
    3536
  ],
  "game_0064.npz": [
    62,
    2563
  ],
  "game_0065.npz": [
    110,
    3201
  ],
  "game_0066.npz": [
    98,
    3044
  ],
  "game_0067.npz": [
    62,
    2523
  ],
  "game_0068.npz": [
    118,
    3302
  ],
  "game_0069.npz": [
    62,
    2563
  ],
  "game_0070.npz": [
    124,
    3373
  ],
  "game_0071.npz": [
    62,
    2557
  ],
  "game_0072.npz": [
    62,
    2559
  ],
  "game_0073.npz": [
    114,
    3216
  ],
  "game_0074.npz": [
    63,
    2517
  ],
  "game_0075.npz": [
    67,
    2673
  ],
  "game_0076.npz": [
    65,
    2621
  ],
  "game_0077.npz": [
    68,
    2624
  ],
  "game_0078.npz": [
    62,
    2539
  ],
  "game_0079.npz": [
    62,
    2526
  ],
  "game_0080.npz": [
    105,
    3174
  ],
  "game_0081.npz": [
    63,
    2563
  ],
  "game_0082.npz": [
    116,
    3258
  ],
  "game_0083.npz": [
    250,
    5132
  ],
  "game_0084.npz": [
    62,
    2504
  ],
  "game_0085.npz": [
    106,
    3098
  ],
  "game_0086.npz": [
    128,
    3446
  ],
  "game_0087.npz": [
    132,
    3518
  ],
  "game_0088.npz": [
    137,
    3611
  ],
  "game_0089.npz": [
    67,
    2639
  ],
  "game_0090.npz": [
    113,
    3263
  ],
  "game_0091.npz": [
    68,
    2646
  ],
  "game_0092.npz": [
    120,
    3367
  ],
  "game_0093.npz": [
    62,
    2551
  ],
  "game_0094.npz": [
    65,
    2584
  ],
  "game_0095.npz": [
    69,
    2695
  ],
  "game_0096.npz": [
    62,
    2498
  ],
  "game_0097.npz": [
    62,
    2549
  ],
  "game_0098.npz": [
    101,
    3163
  ],
  "game_0099.npz": [
    62,
    2552
  ],
  "game_0100.npz": [
    62,
    2535
  ],
  "game_0101.npz": [
    108,
    3186
  ],
  "game_0102.npz": [
    81,
    2845
  ],
  "game_0103.npz": [
    63,
    2562
  ],
  "game_0104.npz": [
    122,
    3327
  ],
  "game_0105.npz": [
    134,
    3500
  ],
  "game_0106.npz": [
    120,
    3392
  ],
  "game_0107.npz": [
    62,
    2521
  ],
  "game_0108.npz": [
    125,
    3396
  ],
  "game_0109.npz": [
    104,
    3138
  ],
  "game_0110.npz": [
    62,
    2555
  ],
  "game_0111.npz": [
    148,
    3691
  ],
  "game_0112.npz": [
    62,
    2557
  ],
  "game_0113.npz": [
    106,
    3216
  ],
  "game_0114.npz": [
    117,
    3313
  ],
  "game_0115.npz": [
    126,
    3400
  ],
  "game_0116.npz": [
    139,
    3638
  ],
  "game_0117.npz": [
    116,
    3274
  ],
  "game_0118.npz": [
    132,
    3469
  ],
  "game_0119.npz": [
    69,
    2611
  ],
  "game_0120.npz": [
    62,
    2565
  ],
  "game_0121.npz": [
    142,
    3618
  ],
  "game_0122.npz": [
    62,
    2524
  ],
  "game_0123.npz": [
    62,
    2556
  ],
  "game_0124.npz": [
    63,
    2501
  ],
  "game_0125.npz": [
    71,
    2677
  ],
  "game_0126.npz": [
    113,
    3250
  ],
  "game_0127.npz": [
    63,
    2561
  ],
  "game_0128.npz": [
    146,
    3643
  ],
  "game_0129.npz": [
    62,
    2546
  ],
  "game_0130.npz": [
    112,
    3183
  ],
  "game_0131.npz": [
    100,
    3112
  ],
  "game_0132.npz": [
    138,
    3595
  ],
  "game_0133.npz": [
    156,
    3761
  ],
  "game_0134.npz": [
    62,
    2561
  ],
  "game_0135.npz": [
    128,
    3417
  ],
  "game_0136.npz": [
    158,
    3890
  ],
  "game_0137.npz": [
    132,
    3432
  ],
  "game_0138.npz": [
    68,
    2617
  ],
  "game_0139.npz": [
    157,
    3830
  ],
  "game_0140.npz": [
    108,
    3213
  ],
  "game_0141.npz": [
    62,
    2568
  ],
  "game_0142.npz": [
    62,
    2508
  ],
  "game_0143.npz": [
    62,
    2518
  ],
  "game_0144.npz": [
    74,
    2722
  ],
  "game_0145.npz": [
    134,
    3440
  ],
  "game_0146.npz": [
    62,
    2539
  ],
  "game_0147.npz": [
    73,
    2719
  ],
  "game_0148.npz": [
    126,
    3433
  ],
  "game_0149.npz": [
    72,
    2685
  ],
  "game_0150.npz": [
    90,
    2959
  ],
  "game_0151.npz": [
    131,
    3505
  ],
  "game_0152.npz": [
    111,
    3211
  ],
  "game_0153.npz": [
    121,
    3372
  ],
  "game_0154.npz": [
    62,
    2557
  ],
  "game_0155.npz": [
    62,
    2515
  ],
  "game_0156.npz": [
    62,
    2541
  ],
  "game_0157.npz": [
    62,
    2544
  ],
  "game_0158.npz": [
    76,
    2790
  ],
  "game_0159.npz": [
    250,
    5105
  ],
  "game_0160.npz": [
    62,
    2548
  ],
  "game_0161.npz": [
    63,
    2570
  ],
  "game_0162.npz": [
    62,
    2542
  ],
  "game_0163.npz": [
    117,
    3281
  ],
  "game_0164.npz": [
    62,
    2568
  ],
  "game_0165.npz": [
    92,
    3032
  ],
  "game_0166.npz": [
    139,
    3612
  ],
  "game_0167.npz": [
    79,
    2799
  ],
  "game_0168.npz": [
    131,
    3584
  ],
  "game_0169.npz": [
    62,
    2572
  ],
  "game_0170.npz": [
    93,
    2952
  ],
  "game_0171.npz": [
    78,
    2785
  ],
  "game_0172.npz": [
    250,
    5037
  ],
  "game_0173.npz": [
    74,
    2730
  ],
  "game_0174.npz": [
    105,
    3168
  ],
  "game_0175.npz": [
    125,
    3449
  ],
  "game_0176.npz": [
    74,
    2702
  ],
  "game_0177.npz": [
    88,
    2871
  ],
  "game_0178.npz": [
    62,
    2518
  ],
  "game_0179.npz": [
    99,
    3058
  ],
  "game_0180.npz": [
    62,
    2549
  ],
  "game_0181.npz": [
    110,
    3170
  ],
  "game_0182.npz": [
    62,
    2518
  ],
  "game_0183.npz": [
    62,
    2570
  ],
  "game_0184.npz": [
    62,
    2554
  ],
  "game_0185.npz": [
    68,
    2642
  ],
  "game_0186.npz": [
    158,
    3903
  ],
  "game_0187.npz": [
    142,
    3677
  ],
  "game_0188.npz": [
    250,
    5068
  ],
  "game_0189.npz": [
    153,
    3750
  ],
  "game_0190.npz": [
    144,
    3730
  ],
  "game_0191.npz": [
    122,
    3364
  ],
  "game_0192.npz": [
    66,
    2640
  ],
  "game_0193.npz": [
    62,
    2513
  ],
  "game_0194.npz": [
    115,
    3284
  ],
  "game_0195.npz": [
    136,
    3529
  ],
  "game_0196.npz": [
    124,
    3433
  ],
  "game_0197.npz": [
    64,
    2594
  ],
  "game_0198.npz": [
    124,
    3400
  ],
  "game_0199.npz": [
    62,
    2501
  ],
  "game_0200.npz": [
    62,
    2504
  ],
  "game_0201.npz": [
    147,
    3740
  ],
  "game_0202.npz": [
    62,
    2554
  ],
  "game_0203.npz": [
    62,
    2586
  ],
  "game_0204.npz": [
    62,
    2514
  ],
  "game_0205.npz": [
    121,
    3362
  ],
  "game_0206.npz": [
    250,
    5129
  ],
  "game_0207.npz": [
    81,
    2817
  ],
  "game_0208.npz": [
    64,
    2592
  ],
  "game_0209.npz": [
    128,
    3458
  ],
  "game_0210.npz": [
    133,
    3457
  ],
  "game_0211.npz": [
    115,
    3333
  ],
  "game_0212.npz": [
    62,
    2546
  ],
  "game_0213.npz": [
    110,
    3211
  ],
  "game_0214.npz": [
    82,
    2799
  ],
  "game_0215.npz": [
    79,
    2794
  ],
  "game_0216.npz": [
    138,
    3658
  ],
  "game_0217.npz": [
    63,
    2566
  ],
  "game_0218.npz": [
    65,
    2540
  ],
  "game_0219.npz": [
    64,
    2580
  ],
  "game_0220.npz": [
    62,
    2579
  ],
  "game_0221.npz": [
    124,
    3355
  ],
  "game_0222.npz": [
    123,
    3364
  ],
  "game_0223.npz": [
    62,
    2486
  ],
  "game_0224.npz": [
    62,
    2532
  ],
  "game_0225.npz": [
    130,
    3509
  ],
  "game_0226.npz": [
    62,
    2525
  ],
  "game_0227.npz": [
    93,
    2967
  ],
  "game_0228.npz": [
    120,
    3351
  ],
  "game_0229.npz": [
    62,
    2546
  ],
  "game_0230.npz": [
    150,
    3723
  ],
  "game_0231.npz": [
    134,
    3513
  ],
  "game_0232.npz": [
    62,
    2557
  ],
  "game_0233.npz": [
    62,
    2540
  ],
  "game_0234.npz": [
    112,
    3260
  ],
  "game_0235.npz": [
    63,
    2539
  ],
  "game_0236.npz": [
    114,
    3225
  ],
  "game_0237.npz": [
    120,
    3348
  ],
  "game_0238.npz": [
    153,
    3769
  ],
  "game_0239.npz": [
    62,
    2591
  ],
  "game_0240.npz": [
    110,
    3232
  ],
  "game_0241.npz": [
    143,
    3634
  ],
  "game_0242.npz": [
    64,
    2581
  ],
  "game_0243.npz": [
    64,
    2599
  ],
  "game_0244.npz": [
    62,
    2532
  ],
  "game_0245.npz": [
    115,
    3255
  ],
  "game_0246.npz": [
    62,
    2561
  ],
  "game_0247.npz": [
    112,
    3246
  ],
  "game_0248.npz": [
    66,
    2612
  ],
  "game_0249.npz": [
    62,
    2571
  ],
  "game_0250.npz": [
    110,
    3191
  ],
  "game_0251.npz": [
    78,
    2816
  ],
  "game_0252.npz": [
    63,
    2521
  ],
  "game_0253.npz": [
    114,
    3262
  ],
  "game_0254.npz": [
    120,
    3337
  ],
  "game_0255.npz": [
    110,
    3228
  ],
  "game_0256.npz": [
    81,
    2807
  ],
  "game_0257.npz": [
    116,
    3267
  ],
  "game_0258.npz": [
    62,
    2542
  ],
  "game_0259.npz": [
    66,
    2579
  ],
  "game_0260.npz": [
    108,
    3179
  ],
  "game_0261.npz": [
    62,
    2548
  ],
  "game_0262.npz": [
    114,
    3218
  ],
  "game_0263.npz": [
    131,
    3513
  ],
  "game_0264.npz": [
    62,
    2555
  ],
  "game_0265.npz": [
    64,
    2606
  ],
  "game_0266.npz": [
    142,
    3569
  ],
  "game_0267.npz": [
    95,
    3045
  ],
  "game_0268.npz": [
    66,
    2590
  ],
  "game_0269.npz": [
    62,
    2556
  ],
  "game_0270.npz": [
    62,
    2488
  ],
  "game_0271.npz": [
    62,
    2540
  ],
  "game_0272.npz": [
    86,
    2916
  ],
  "game_0273.npz": [
    135,
    3590
  ],
  "game_0274.npz": [
    62,
    2517
  ],
  "game_0275.npz": [
    62,
    2547
  ],
  "game_0276.npz": [
    143,
    3708
  ],
  "game_0277.npz": [
    62,
    2532
  ],
  "game_0278.npz": [
    152,
    3714
  ],
  "game_0279.npz": [
    62,
    2558
  ],
  "game_0280.npz": [
    107,
    3180
  ],
  "game_0281.npz": [
    113,
    3303
  ],
  "game_0282.npz": [
    143,
    3710
  ],
  "game_0283.npz": [
    64,
    2608
  ],
  "game_0284.npz": [
    62,
    2500
  ],
  "game_0285.npz": [
    62,
    2581
  ],
  "game_0286.npz": [
    62,
    2542
  ],
  "game_0287.npz": [
    62,
    2518
  ],
  "game_0288.npz": [
    62,
    2584
  ],
  "game_0289.npz": [
    62,
    2554
  ],
  "game_0290.npz": [
    62,
    2550
  ],
  "game_0291.npz": [
    62,
    2527
  ],
  "game_0292.npz": [
    62,
    2567
  ],
  "game_0293.npz": [
    64,
    2585
  ],
  "game_0294.npz": [
    62,
    2513
  ],
  "game_0295.npz": [
    138,
    3615
  ],
  "game_0296.npz": [
    130,
    3471
  ],
  "game_0297.npz": [
    63,
    2526
  ],
  "game_0298.npz": [
    144,
    3744
  ],
  "game_0299.npz": [
    62,
    2579
  ],
  "game_0300.npz": [
    62,
    2529
  ],
  "game_0301.npz": [
    121,
    3364
  ],
  "game_0302.npz": [
    62,
    2526
  ],
  "game_0303.npz": [
    62,
    2537
  ],
  "game_0304.npz": [
    82,
    2785
  ],
  "game_0305.npz": [
    62,
    2531
  ],
  "game_0306.npz": [
    64,
    2567
  ],
  "game_0307.npz": [
    151,
    3756
  ],
  "game_0308.npz": [
    155,
    3792
  ],
  "game_0309.npz": [
    62,
    2522
  ],
  "game_0310.npz": [
    139,
    3578
  ],
  "game_0311.npz": [
    149,
    3743
  ],
  "game_0312.npz": [
    124,
    3406
  ],
  "game_0313.npz": [
    66,
    2639
  ],
  "game_0314.npz": [
    135,
    3529
  ],
  "game_0315.npz": [
    65,
    2575
  ],
  "game_0316.npz": [
    139,
    3575
  ],
  "game_0317.npz": [
    143,
    3771
  ],
  "game_0318.npz": [
    94,
    2978
  ],
  "game_0319.npz": [
    116,
    3323
  ],
  "game_0320.npz": [
    141,
    3597
  ],
  "game_0321.npz": [
    62,
    2561
  ],
  "game_0322.npz": [
    62,
    2542
  ],
  "game_0323.npz": [
    111,
    3239
  ],
  "game_0324.npz": [
    62,
    2535
  ],
  "game_0325.npz": [
    128,
    3406
  ],
  "game_0326.npz": [
    131,
    3485
  ],
  "game_0327.npz": [
    67,
    2584
  ],
  "game_0328.npz": [
    122,
    3309
  ],
  "game_0329.npz": [
    64,
    2615
  ],
  "game_0330.npz": [
    66,
    2588
  ],
  "game_0331.npz": [
    62,
    2579
  ],
  "game_0332.npz": [
    62,
    2523
  ],
  "game_0333.npz": [
    125,
    3437
  ],
  "game_0334.npz": [
    62,
    2541
  ],
  "game_0335.npz": [
    62,
    2555
  ],
  "game_0336.npz": [
    113,
    3248
  ],
  "game_0337.npz": [
    137,
    3573
  ],
  "game_0338.npz": [
    81,
    2833
  ],
  "game_0339.npz": [
    64,
    2569
  ],
  "game_0340.npz": [
    114,
    3262
  ],
  "game_0341.npz": [
    132,
    3475
  ],
  "game_0342.npz": [
    64,
    2605
  ],
  "game_0343.npz": [
    62,
    2520
  ],
  "game_0344.npz": [
    63,
    2603
  ],
  "game_0345.npz": [
    121,
    3369
  ],
  "game_0346.npz": [
    126,
    3441
  ],
  "game_0347.npz": [
    138,
    3548
  ],
  "game_0348.npz": [
    112,
    3194
  ],
  "game_0349.npz": [
    121,
    3357
  ],
  "game_0350.npz": [
    151,
    3748
  ],
  "game_0351.npz": [
    136,
    3587
  ],
  "game_0352.npz": [
    62,
    2532
  ],
  "game_0353.npz": [
    122,
    3353
  ],
  "game_0354.npz": [
    70,
    2610
  ],
  "game_0355.npz": [
    121,
    3373
  ],
  "game_0356.npz": [
    132,
    3520
  ],
  "game_0357.npz": [
    150,
    3702
  ],
  "game_0358.npz": [
    142,
    3601
  ],
  "game_0359.npz": [
    122,
    3348
  ],
  "game_0360.npz": [
    146,
    3665
  ],
  "game_0361.npz": [
    151,
    3740
  ],
  "game_0362.npz": [
    62,
    2516
  ],
  "game_0363.npz": [
    124,
    3378
  ],
  "game_0364.npz": [
    62,
    2552
  ],
  "game_0365.npz": [
    64,
    2550
  ],
  "game_0366.npz": [
    62,
    2547
  ],
  "game_0367.npz": [
    130,
    3469
  ],
  "game_0368.npz": [
    116,
    3256
  ],
  "game_0369.npz": [
    64,
    2580
  ],
  "game_0370.npz": [
    62,
    2548
  ],
  "game_0371.npz": [
    81,
    2830
  ],
  "game_0372.npz": [
    84,
    2821
  ],
  "game_0373.npz": [
    90,
    2944
  ],
  "game_0374.npz": [
    78,
    2763
  ],
  "game_0375.npz": [
    66,
    2565
  ],
  "game_0376.npz": [
    62,
    2484
  ],
  "game_0377.npz": [
    62,
    2527
  ],
  "game_0378.npz": [
    125,
    3443
  ],
  "game_0379.npz": [
    110,
    3190
  ],
  "game_0380.npz": [
    161,
    3931
  ],
  "game_0381.npz": [
    66,
    2578
  ],
  "game_0382.npz": [
    62,
    2550
  ],
  "game_0383.npz": [
    138,
    3528
  ],
  "game_0384.npz": [
    152,
    3767
  ],
  "game_0385.npz": [
    116,
    3287
  ],
  "game_0386.npz": [
    62,
    2526
  ],
  "game_0387.npz": [
    63,
    2545
  ],
  "game_0388.npz": [
    90,
    2921
  ],
  "game_0389.npz": [
    143,
    3636
  ],
  "game_0390.npz": [
    70,
    2654
  ],
  "game_0391.npz": [
    140,
    3626
  ],
  "game_0392.npz": [
    154,
    3786
  ],
  "game_0393.npz": [
    132,
    3505
  ],
  "game_0394.npz": [
    62,
    2557
  ],
  "game_0395.npz": [
    64,
    2540
  ],
  "game_0396.npz": [
    64,
    2571
  ],
  "game_0397.npz": [
    62,
    2566
  ],
  "game_0398.npz": [
    128,
    3438
  ],
  "game_0399.npz": [
    63,
    2581
  ],
  "game_0400.npz": [
    112,
    3208
  ],
  "game_0401.npz": [
    140,
    3578
  ],
  "game_0402.npz": [
    62,
    2554
  ],
  "game_0403.npz": [
    113,
    3238
  ],
  "game_0404.npz": [
    62,
    2524
  ],
  "game_0405.npz": [
    133,
    3606
  ],
  "game_0406.npz": [
    62,
    2550
  ],
  "game_0407.npz": [
    62,
    2567
  ],
  "game_0408.npz": [
    112,
    3228
  ],
  "game_0409.npz": [
    116,
    3258
  ],
  "game_0410.npz": [
    112,
    3218
  ],
  "game_0411.npz": [
    109,
    3183
  ],
  "game_0412.npz": [
    71,
    2672
  ],
  "game_0413.npz": [
    62,
    2522
  ],
  "game_0414.npz": [
    79,
    2800
  ],
  "game_0415.npz": [
    62,
    2560
  ],
  "game_0416.npz": [
    129,
    3428
  ],
  "game_0417.npz": [
    130,
    3520
  ],
  "game_0418.npz": [
    129,
    3454
  ],
  "game_0419.npz": [
    62,
    2531
  ],
  "game_0420.npz": [
    129,
    3517
  ],
  "game_0421.npz": [
    62,
    2523
  ],
  "game_0422.npz": [
    62,
    2529
  ],
  "game_0423.npz": [
    62,
    2562
  ],
  "game_0424.npz": [
    62,
    2552
  ],
  "game_0425.npz": [
    62,
    2545
  ],
  "game_0426.npz": [
    62,
    2559
  ],
  "game_0427.npz": [
    64,
    2574
  ],
  "game_0428.npz": [
    148,
    3738
  ],
  "game_0429.npz": [
    135,
    3549
  ],
  "game_0430.npz": [
    62,
    2541
  ],
  "game_0431.npz": [
    62,
    2552
  ],
  "game_0432.npz": [
    84,
    2855
  ],
  "game_0433.npz": [
    62,
    2464
  ],
  "game_0434.npz": [
    110,
    3194
  ],
  "game_0435.npz": [
    73,
    2715
  ],
  "game_0436.npz": [
    113,
    3286
  ],
  "game_0437.npz": [
    113,
    3244
  ],
  "game_0438.npz": [
    65,
    2559
  ],
  "game_0439.npz": [
    80,
    2830
  ],
  "game_0440.npz": [
    62,
    2528
  ],
  "game_0441.npz": [
    62,
    2499
  ],
  "game_0442.npz": [
    134,
    3489
  ],
  "game_0443.npz": [
    98,
    3056
  ],
  "game_0444.npz": [
    137,
    3572
  ],
  "game_0445.npz": [
    62,
    2506
  ],
  "game_0446.npz": [
    62,
    2547
  ],
  "game_0447.npz": [
    62,
    2512
  ],
  "game_0448.npz": [
    62,
    2567
  ],
  "game_0449.npz": [
    130,
    3447
  ],
  "game_0450.npz": [
    111,
    3215
  ],
  "game_0451.npz": [
    62,
    2497
  ],
  "game_0452.npz": [
    62,
    2526
  ],
  "game_0453.npz": [
    126,
    3460
  ],
  "game_0454.npz": [
    66,
    2613
  ],
  "game_0455.npz": [
    62,
    2551
  ],
  "game_0456.npz": [
    64,
    2612
  ],
  "game_0457.npz": [
    62,
    2519
  ],
  "game_0458.npz": [
    122,
    3346
  ],
  "game_0459.npz": [
    121,
    3349
  ],
  "game_0460.npz": [
    134,
    3478
  ],
  "game_0461.npz": [
    135,
    3524
  ],
  "game_0462.npz": [
    114,
    3239
  ],
  "game_0463.npz": [
    62,
    2519
  ],
  "game_0464.npz": [
    63,
    2582
  ],
  "game_0465.npz": [
    77,
    2796
  ],
  "game_0466.npz": [
    96,
    3032
  ],
  "game_0467.npz": [
    62,
    2500
  ],
  "game_0468.npz": [
    63,
    2563
  ],
  "game_0469.npz": [
    145,
    3752
  ],
  "game_0470.npz": [
    146,
    3706
  ],
  "game_0471.npz": [
    74,
    2730
  ],
  "game_0472.npz": [
    62,
    2596
  ],
  "game_0473.npz": [
    106,
    3133
  ],
  "game_0474.npz": [
    149,
    3768
  ],
  "game_0475.npz": [
    62,
    2536
  ],
  "game_0476.npz": [
    62,
    2533
  ],
  "game_0477.npz": [
    148,
    3710
  ],
  "game_0478.npz": [
    145,
    3656
  ],
  "game_0479.npz": [
    62,
    2564
  ],
  "game_0480.npz": [
    133,
    3487
  ],
  "game_0481.npz": [
    135,
    3524
  ],
  "game_0482.npz": [
    62,
    2504
  ],
  "game_0483.npz": [
    63,
    2550
  ],
  "game_0484.npz": [
    62,
    2535
  ],
  "game_0485.npz": [
    68,
    2670
  ],
  "game_0486.npz": [
    62,
    2551
  ],
  "game_0487.npz": [
    67,
    2685
  ],
  "game_0488.npz": [
    150,
    3716
  ],
  "game_0489.npz": [
    148,
    3702
  ],
  "game_0490.npz": [
    115,
    3227
  ],
  "game_0491.npz": [
    116,
    3288
  ],
  "game_0492.npz": [
    127,
    3466
  ],
  "game_0493.npz": [
    62,
    2555
  ],
  "game_0494.npz": [
    65,
    2605
  ],
  "game_0495.npz": [
    123,
    3366
  ],
  "game_0496.npz": [
    62,
    2570
  ],
  "game_0497.npz": [
    77,
    2781
  ],
  "game_0498.npz": [
    146,
    3656
  ],
  "game_0499.npz": [
    62,
    2505
  ],
  "game_0500.npz": [
    62,
    2534
  ],
  "game_0501.npz": [
    62,
    2501
  ],
  "game_0502.npz": [
    63,
    2599
  ],
  "game_0503.npz": [
    84,
    2843
  ],
  "game_0504.npz": [
    115,
    3297
  ],
  "game_0505.npz": [
    62,
    2543
  ],
  "game_0506.npz": [
    62,
    2558
  ],
  "game_0507.npz": [
    68,
    2657
  ],
  "game_0508.npz": [
    128,
    3507
  ],
  "game_0509.npz": [
    131,
    3480
  ],
  "game_0510.npz": [
    105,
    3148
  ],
  "game_0511.npz": [
    134,
    3591
  ],
  "game_0512.npz": [
    67,
    2566
  ],
  "game_0513.npz": [
    105,
    3168
  ],
  "game_0514.npz": [
    128,
    3443
  ],
  "game_0515.npz": [
    64,
    2548
  ],
  "game_0516.npz": [
    137,
    3620
  ],
  "game_0517.npz": [
    68,
    2642
  ],
  "game_0518.npz": [
    62,
    2505
  ],
  "game_0519.npz": [
    133,
    3516
  ],
  "game_0520.npz": [
    63,
    2515
  ],
  "game_0521.npz": [
    62,
    2533
  ],
  "game_0522.npz": [
    101,
    3096
  ],
  "game_0523.npz": [
    144,
    3639
  ],
  "game_0524.npz": [
    129,
    3471
  ],
  "game_0525.npz": [
    131,
    3577
  ],
  "game_0526.npz": [
    113,
    3316
  ],
  "game_0527.npz": [
    62,
    2543
  ],
  "game_0528.npz": [
    63,
    2558
  ],
  "game_0529.npz": [
    82,
    2833
  ],
  "game_0530.npz": [
    137,
    3579
  ],
  "game_0531.npz": [
    74,
    2726
  ],
  "game_0532.npz": [
    90,
    2944
  ],
  "game_0533.npz": [
    67,
    2653
  ],
  "game_0534.npz": [
    68,
    2684
  ],
  "game_0535.npz": [
    135,
    3544
  ],
  "game_0536.npz": [
    62,
    2587
  ],
  "game_0537.npz": [
    72,
    2734
  ],
  "game_0538.npz": [
    114,
    3267
  ],
  "game_0539.npz": [
    111,
    3210
  ],
  "game_0540.npz": [
    250,
    5003
  ],
  "game_0541.npz": [
    89,
    2992
  ],
  "game_0542.npz": [
    118,
    3336
  ],
  "game_0543.npz": [
    145,
    3656
  ],
  "game_0544.npz": [
    105,
    3145
  ],
  "game_0545.npz": [
    62,
    2527
  ],
  "game_0546.npz": [
    64,
    2621
  ],
  "game_0547.npz": [
    62,
    2552
  ],
  "game_0548.npz": [
    63,
    2577
  ],
  "game_0549.npz": [
    128,
    3388
  ],
  "game_0550.npz": [
    106,
    3143
  ],
  "game_0551.npz": [
    76,
    2758
  ],
  "game_0552.npz": [
    66,
    2597
  ],
  "game_0553.npz": [
    150,
    3805
  ],
  "game_0554.npz": [
    62,
    2515
  ],
  "game_0555.npz": [
    132,
    3493
  ],
  "game_0556.npz": [
    62,
    2564
  ],
  "game_0557.npz": [
    148,
    3786
  ],
  "game_0558.npz": [
    123,
    3394
  ],
  "game_0559.npz": [
    107,
    3195
  ],
  "game_0560.npz": [
    64,
    2624
  ],
  "game_0561.npz": [
    125,
    3421
  ],
  "game_0562.npz": [
    62,
    2553
  ],
  "game_0563.npz": [
    62,
    2545
  ],
  "game_0564.npz": [
    62,
    2540
  ],
  "game_0565.npz": [
    62,
    2536
  ],
  "game_0566.npz": [
    62,
    2595
  ],
  "game_0567.npz": [
    126,
    3405
  ],
  "game_0568.npz": [
    133,
    3491
  ],
  "game_0569.npz": [
    119,
    3288
  ],
  "game_0570.npz": [
    131,
    3504
  ],
  "game_0571.npz": [
    64,
    2619
  ],
  "game_0572.npz": [
    152,
    3757
  ],
  "game_0573.npz": [
    134,
    3482
  ],
  "game_0574.npz": [
    148,
    3643
  ],
  "game_0575.npz": [
    117,
    3281
  ],
  "game_0576.npz": [
    62,
    2560
  ],
  "game_0577.npz": [
    151,
    3766
  ],
  "game_0578.npz": [
    106,
    3155
  ],
  "game_0579.npz": [
    66,
    2574
  ],
  "game_0580.npz": [
    162,
    3859
  ],
  "game_0581.npz": [
    62,
    2539
  ],
  "game_0582.npz": [
    83,
    2862
  ],
  "game_0583.npz": [
    64,
    2573
  ],
  "game_0584.npz": [
    63,
    2558
  ],
  "game_0585.npz": [
    62,
    2526
  ],
  "game_0586.npz": [
    144,
    3688
  ],
  "game_0587.npz": [
    62,
    2566
  ],
  "game_0588.npz": [
    114,
    3219
  ],
  "game_0589.npz": [
    122,
    3292
  ],
  "game_0590.npz": [
    62,
    2533
  ],
  "game_0591.npz": [
    106,
    3184
  ],
  "game_0592.npz": [
    74,
    2700
  ],
  "game_0593.npz": [
    124,
    3470
  ],
  "game_0594.npz": [
    62,
    2508
  ],
  "game_0595.npz": [
    114,
    3257
  ],
  "game_0596.npz": [
    63,
    2597
  ],
  "game_0597.npz": [
    114,
    3245
  ],
  "game_0598.npz": [
    147,
    3746
  ],
  "game_0599.npz": [
    62,
    2566
  ],
  "game_0600.npz": [
    154,
    3835
  ],
  "game_0601.npz": [
    111,
    3196
  ],
  "game_0602.npz": [
    127,
    3468
  ],
  "game_0603.npz": [
    144,
    3666
  ],
  "game_0604.npz": [
    111,
    3169
  ],
  "game_0605.npz": [
    119,
    3366
  ],
  "game_0606.npz": [
    70,
    2686
  ],
  "game_0607.npz": [
    124,
    3426
  ],
  "game_0608.npz": [
    67,
    2637
  ],
  "game_0609.npz": [
    65,
    2589
  ],
  "game_0610.npz": [
    135,
    3534
  ],
  "game_0611.npz": [
    129,
    3475
  ],
  "game_0612.npz": [
    138,
    3531
  ],
  "game_0613.npz": [
    127,
    3464
  ],
  "game_0614.npz": [
    129,
    3487
  ],
  "game_0615.npz": [
    115,
    3277
  ],
  "game_0616.npz": [
    64,
    2603
  ],
  "game_0617.npz": [
    150,
    3818
  ],
  "game_0618.npz": [
    122,
    3376
  ],
  "game_0619.npz": [
    62,
    2567
  ],
  "game_0620.npz": [
    250,
    5171
  ],
  "game_0621.npz": [
    129,
    3486
  ],
  "game_0622.npz": [
    62,
    2534
  ],
  "game_0623.npz": [
    151,
    3792
  ],
  "game_0624.npz": [
    62,
    2514
  ],
  "game_0625.npz": [
    90,
    2921
  ],
  "game_0626.npz": [
    100,
    3050
  ],
  "game_0627.npz": [
    128,
    3386
  ],
  "game_0628.npz": [
    62,
    2558
  ],
  "game_0629.npz": [
    142,
    3638
  ],
  "game_0630.npz": [
    62,
    2588
  ],
  "game_0631.npz": [
    122,
    3299
  ],
  "game_0632.npz": [
    62,
    2553
  ],
  "game_0633.npz": [
    64,
    2590
  ],
  "game_0634.npz": [
    108,
    3156
  ],
  "game_0635.npz": [
    119,
    3412
  ],
  "game_0636.npz": [
    62,
    2540
  ],
  "game_0637.npz": [
    250,
    5097
  ],
  "game_0638.npz": [
    62,
    2524
  ],
  "game_0639.npz": [
    62,
    2556
  ],
  "game_0640.npz": [
    69,
    2666
  ],
  "game_0641.npz": [
    137,
    3579
  ],
  "game_0642.npz": [
    62,
    2550
  ],
  "game_0643.npz": [
    62,
    2537
  ],
  "game_0644.npz": [
    62,
    2545
  ],
  "game_0645.npz": [
    160,
    3859
  ],
  "game_0646.npz": [
    62,
    2530
  ],
  "game_0647.npz": [
    148,
    3642
  ],
  "game_0648.npz": [
    108,
    3154
  ],
  "game_0649.npz": [
    141,
    3658
  ],
  "game_0650.npz": [
    110,
    3275
  ],
  "game_0651.npz": [
    126,
    3416
  ],
  "game_0652.npz": [
    62,
    2542
  ],
  "game_0653.npz": [
    125,
    3419
  ],
  "game_0654.npz": [
    87,
    2936
  ],
  "game_0655.npz": [
    151,
    3888
  ],
  "game_0656.npz": [
    62,
    2594
  ],
  "game_0657.npz": [
    131,
    3451
  ],
  "game_0658.npz": [
    128,
    3459
  ],
  "game_0659.npz": [
    139,
    3609
  ],
  "game_0660.npz": [
    145,
    3710
  ],
  "game_0661.npz": [
    143,
    3704
  ],
  "game_0662.npz": [
    77,
    2740
  ],
  "game_0663.npz": [
    62,
    2526
  ],
  "game_0664.npz": [
    62,
    2543
  ],
  "game_0665.npz": [
    65,
    2623
  ],
  "game_0666.npz": [
    64,
    2576
  ],
  "game_0667.npz": [
    106,
    3149
  ],
  "game_0668.npz": [
    62,
    2530
  ],
  "game_0669.npz": [
    142,
    3648
  ],
  "game_0670.npz": [
    62,
    2585
  ],
  "game_0671.npz": [
    123,
    3358
  ],
  "game_0672.npz": [
    62,
    2541
  ],
  "game_0673.npz": [
    85,
    2916
  ],
  "game_0674.npz": [
    134,
    3622
  ],
  "game_0675.npz": [
    62,
    2576
  ],
  "game_0676.npz": [
    68,
    2677
  ],
  "game_0677.npz": [
    62,
    2529
  ],
  "game_0678.npz": [
    130,
    3468
  ],
  "game_0679.npz": [
    140,
    3606
  ],
  "game_0680.npz": [
    124,
    3484
  ],
  "game_0681.npz": [
    108,
    3176
  ],
  "game_0682.npz": [
    137,
    3589
  ],
  "game_0683.npz": [
    132,
    3476
  ],
  "game_0684.npz": [
    62,
    2526
  ],
  "game_0685.npz": [
    62,
    2529
  ],
  "game_0686.npz": [
    131,
    3501
  ],
  "game_0687.npz": [
    62,
    2507
  ],
  "game_0688.npz": [
    135,
    3573
  ],
  "game_0689.npz": [
    62,
    2542
  ],
  "game_0690.npz": [
    135,
    3534
  ],
  "game_0691.npz": [
    133,
    3580
  ],
  "game_0692.npz": [
    62,
    2522
  ],
  "game_0693.npz": [
    127,
    3443
  ],
  "game_0694.npz": [
    64,
    2577
  ],
  "game_0695.npz": [
    134,
    3526
  ],
  "game_0696.npz": [
    62,
    2477
  ],
  "game_0697.npz": [
    140,
    3580
  ],
  "game_0698.npz": [
    122,
    3382
  ],
  "game_0699.npz": [
    109,
    3237
  ],
  "game_0700.npz": [
    64,
    2552
  ],
  "game_0701.npz": [
    145,
    3621
  ],
  "game_0702.npz": [
    64,
    2592
  ],
  "game_0703.npz": [
    62,
    2507
  ],
  "game_0704.npz": [
    63,
    2544
  ],
  "game_0705.npz": [
    144,
    3603
  ],
  "game_0706.npz": [
    62,
    2544
  ],
  "game_0707.npz": [
    62,
    2511
  ],
  "game_0708.npz": [
    68,
    2645
  ],
  "game_0709.npz": [
    78,
    2787
  ],
  "game_0710.npz": [
    151,
    3814
  ],
  "game_0711.npz": [
    62,
    2510
  ],
  "game_0712.npz": [
    66,
    2631
  ],
  "game_0713.npz": [
    139,
    3581
  ],
  "game_0714.npz": [
    250,
    5070
  ],
  "game_0715.npz": [
    62,
    2579
  ],
  "game_0716.npz": [
    133,
    3509
  ],
  "game_0717.npz": [
    66,
    2567
  ],
  "game_0718.npz": [
    113,
    3285
  ],
  "game_0719.npz": [
    87,
    2911
  ],
  "game_0720.npz": [
    111,
    3206
  ],
  "game_0721.npz": [
    117,
    3294
  ],
  "game_0722.npz": [
    65,
    2550
  ],
  "game_0723.npz": [
    65,
    2567
  ],
  "game_0724.npz": [
    62,
    2511
  ],
  "game_0725.npz": [
    62,
    2549
  ],
  "game_0726.npz": [
    131,
    3473
  ],
  "game_0727.npz": [
    62,
    2540
  ],
  "game_0728.npz": [
    62,
    2535
  ],
  "game_0729.npz": [
    62,
    2530
  ],
  "game_0730.npz": [
    65,
    2588
  ],
  "game_0731.npz": [
    62,
    2519
  ],
  "game_0732.npz": [
    122,
    3322
  ],
  "game_0733.npz": [
    62,
    2494
  ],
  "game_0734.npz": [
    138,
    3545
  ],
  "game_0735.npz": [
    103,
    3176
  ],
  "game_0736.npz": [
    62,
    2486
  ],
  "game_0737.npz": [
    110,
    3158
  ],
  "game_0738.npz": [
    62,
    2552
  ],
  "game_0739.npz": [
    137,
    3541
  ],
  "game_0740.npz": [
    62,
    2539
  ],
  "game_0741.npz": [
    112,
    3256
  ],
  "game_0742.npz": [
    100,
    3053
  ],
  "game_0743.npz": [
    62,
    2546
  ],
  "game_0744.npz": [
    62,
    2539
  ],
  "game_0745.npz": [
    64,
    2601
  ],
  "game_0746.npz": [
    62,
    2528
  ],
  "game_0747.npz": [
    62,
    2508
  ],
  "game_0748.npz": [
    62,
    2526
  ],
  "game_0749.npz": [
    125,
    3384
  ],
  "game_0750.npz": [
    63,
    2583
  ],
  "game_0751.npz": [
    62,
    2501
  ],
  "game_0752.npz": [
    62,
    2509
  ],
  "game_0753.npz": [
    114,
    3229
  ],
  "game_0754.npz": [
    66,
    2591
  ],
  "game_0755.npz": [
    148,
    3670
  ],
  "game_0756.npz": [
    144,
    3714
  ],
  "game_0757.npz": [
    99,
    3099
  ],
  "game_0758.npz": [
    126,
    3409
  ],
  "game_0759.npz": [
    92,
    2900
  ],
  "game_0760.npz": [
    128,
    3429
  ],
  "game_0761.npz": [
    103,
    3142
  ],
  "game_0762.npz": [
    62,
    2545
  ],
  "game_0763.npz": [
    139,
    3570
  ],
  "game_0764.npz": [
    116,
    3240
  ],
  "game_0765.npz": [
    62,
    2599
  ],
  "game_0766.npz": [
    66,
    2589
  ],
  "game_0767.npz": [
    80,
    2798
  ],
  "game_0768.npz": [
    118,
    3326
  ],
  "game_0769.npz": [
    62,
    2481
  ],
  "game_0770.npz": [
    242,
    5050
  ],
  "game_0771.npz": [
    136,
    3620
  ],
  "game_0772.npz": [
    62,
    2562
  ],
  "game_0773.npz": [
    64,
    2585
  ],
  "game_0774.npz": [
    156,
    3824
  ],
  "game_0775.npz": [
    130,
    3443
  ],
  "game_0776.npz": [
    67,
    2632
  ],
  "game_0777.npz": [
    64,
    2560
  ],
  "game_0778.npz": [
    62,
    2568
  ],
  "game_0779.npz": [
    153,
    3880
  ],
  "game_0780.npz": [
    126,
    3449
  ],
  "game_0781.npz": [
    149,
    3733
  ],
  "game_0782.npz": [
    134,
    3544
  ],
  "game_0783.npz": [
    78,
    2804
  ],
  "game_0784.npz": [
    62,
    2571
  ],
  "game_0785.npz": [
    150,
    3696
  ],
  "game_0786.npz": [
    96,
    3073
  ],
  "game_0787.npz": [
    64,
    2589
  ],
  "game_0788.npz": [
    62,
    2509
  ],
  "game_0789.npz": [
    71,
    2751
  ],
  "game_0790.npz": [
    62,
    2534
  ],
  "game_0791.npz": [
    112,
    3224
  ],
  "game_0792.npz": [
    103,
    3141
  ],
  "game_0793.npz": [
    66,
    2549
  ],
  "game_0794.npz": [
    105,
    3161
  ],
  "game_0795.npz": [
    120,
    3312
  ],
  "game_0796.npz": [
    149,
    3738
  ],
  "game_0797.npz": [
    64,
    2618
  ],
  "game_0798.npz": [
    62,
    2546
  ],
  "game_0799.npz": [
    62,
    2558
  ],
  "game_0800.npz": [
    113,
    3281
  ],
  "game_0801.npz": [
    122,
    3406
  ],
  "game_0802.npz": [
    62,
    2559
  ],
  "game_0803.npz": [
    62,
    2523
  ],
  "game_0804.npz": [
    114,
    3301
  ],
  "game_0805.npz": [
    134,
    3483
  ],
  "game_0806.npz": [
    137,
    3593
  ],
  "game_0807.npz": [
    98,
    3068
  ],
  "game_0808.npz": [
    125,
    3389
  ],
  "game_0809.npz": [
    148,
    3728
  ],
  "game_0810.npz": [
    114,
    3255
  ],
  "game_0811.npz": [
    62,
    2509
  ],
  "game_0812.npz": [
    87,
    2899
  ],
  "game_0813.npz": [
    62,
    2526
  ],
  "game_0814.npz": [
    117,
    3317
  ],
  "game_0815.npz": [
    144,
    3624
  ],
  "game_0816.npz": [
    102,
    3109
  ],
  "game_0817.npz": [
    65,
    2612
  ],
  "game_0818.npz": [
    62,
    2544
  ],
  "game_0819.npz": [
    62,
    2526
  ],
  "game_0820.npz": [
    150,
    3781
  ],
  "game_0821.npz": [
    133,
    3515
  ],
  "game_0822.npz": [
    62,
    2556
  ],
  "game_0823.npz": [
    62,
    2551
  ],
  "game_0824.npz": [
    62,
    2567
  ],
  "game_0825.npz": [
    62,
    2551
  ],
  "game_0826.npz": [
    70,
    2680
  ],
  "game_0827.npz": [
    128,
    3428
  ],
  "game_0828.npz": [
    66,
    2623
  ],
  "game_0829.npz": [
    109,
    3124
  ],
  "game_0830.npz": [
    110,
    3166
  ],
  "game_0831.npz": [
    62,
    2638
  ],
  "game_0832.npz": [
    62,
    2541
  ],
  "game_0833.npz": [
    64,
    2602
  ],
  "game_0834.npz": [
    63,
    2520
  ],
  "game_0835.npz": [
    62,
    2535
  ],
  "game_0836.npz": [
    140,
    3583
  ],
  "game_0837.npz": [
    119,
    3309
  ],
  "game_0838.npz": [
    139,
    3563
  ],
  "game_0839.npz": [
    62,
    2543
  ],
  "game_0840.npz": [
    132,
    3534
  ],
  "game_0841.npz": [
    120,
    3370
  ],
  "game_0842.npz": [
    130,
    3502
  ],
  "game_0843.npz": [
    64,
    2593
  ],
  "game_0844.npz": [
    67,
    2618
  ],
  "game_0845.npz": [
    145,
    3632
  ],
  "game_0846.npz": [
    62,
    2558
  ],
  "game_0847.npz": [
    125,
    3435
  ],
  "game_0848.npz": [
    62,
    2551
  ],
  "game_0849.npz": [
    63,
    2589
  ],
  "game_0850.npz": [
    62,
    2555
  ],
  "game_0851.npz": [
    62,
    2576
  ],
  "game_0852.npz": [
    113,
    3217
  ],
  "game_0853.npz": [
    89,
    2943
  ],
  "game_0854.npz": [
    108,
    3212
  ],
  "game_0855.npz": [
    62,
    2499
  ],
  "game_0856.npz": [
    62,
    2572
  ],
  "game_0857.npz": [
    133,
    3548
  ],
  "game_0858.npz": [
    67,
    2626
  ],
  "game_0859.npz": [
    62,
    2507
  ],
  "game_0860.npz": [
    134,
    3497
  ],
  "game_0861.npz": [
    110,
    3209
  ],
  "game_0862.npz": [
    62,
    2531
  ],
  "game_0863.npz": [
    123,
    3410
  ],
  "game_0864.npz": [
    95,
    2987
  ],
  "game_0865.npz": [
    133,
    3502
  ],
  "game_0866.npz": [
    62,
    2535
  ],
  "game_0867.npz": [
    62,
    2575
  ],
  "game_0868.npz": [
    109,
    3241
  ],
  "game_0869.npz": [
    62,
    2537
  ],
  "game_0870.npz": [
    64,
    2583
  ],
  "game_0871.npz": [
    62,
    2538
  ],
  "game_0872.npz": [
    68,
    2690
  ],
  "game_0873.npz": [
    62,
    2550
  ],
  "game_0874.npz": [
    137,
    3607
  ],
  "game_0875.npz": [
    62,
    2566
  ],
  "game_0876.npz": [
    104,
    3136
  ],
  "game_0877.npz": [
    62,
    2537
  ],
  "game_0878.npz": [
    62,
    2578
  ],
  "game_0879.npz": [
    62,
    2507
  ],
  "game_0880.npz": [
    62,
    2542
  ],
  "game_0881.npz": [
    62,
    2555
  ],
  "game_0882.npz": [
    66,
    2585
  ],
  "game_0883.npz": [
    62,
    2560
  ],
  "game_0884.npz": [
    62,
    2524
  ],
  "game_0885.npz": [
    64,
    2597
  ],
  "game_0886.npz": [
    122,
    3354
  ],
  "game_0887.npz": [
    132,
    3540
  ],
  "game_0888.npz": [
    250,
    5101
  ],
  "game_0889.npz": [
    144,
    3786
  ],
  "game_0890.npz": [
    62,
    2564
  ],
  "game_0891.npz": [
    163,
    3832
  ],
  "game_0892.npz": [
    62,
    2558
  ],
  "game_0893.npz": [
    98,
    3048
  ],
  "game_0894.npz": [
    154,
    3772
  ],
  "game_0895.npz": [
    94,
    2950
  ],
  "game_0896.npz": [
    62,
    2489
  ],
  "game_0897.npz": [
    62,
    2564
  ],
  "game_0898.npz": [
    139,
    3596
  ],
  "game_0899.npz": [
    62,
    2573
  ],
  "game_0900.npz": [
    250,
    5156
  ],
  "game_0901.npz": [
    64,
    2611
  ],
  "game_0902.npz": [
    93,
    2969
  ],
  "game_0903.npz": [
    128,
    3411
  ],
  "game_0904.npz": [
    130,
    3505
  ],
  "game_0905.npz": [
    124,
    3408
  ],
  "game_0906.npz": [
    103,
    3124
  ],
  "game_0907.npz": [
    62,
    2581
  ],
  "game_0908.npz": [
    141,
    3671
  ],
  "game_0909.npz": [
    62,
    2571
  ],
  "game_0910.npz": [
    111,
    3159
  ],
  "game_0911.npz": [
    103,
    3119
  ],
  "game_0912.npz": [
    76,
    2767
  ],
  "game_0913.npz": [
    63,
    2524
  ],
  "game_0914.npz": [
    119,
    3282
  ],
  "game_0915.npz": [
    137,
    3510
  ],
  "game_0916.npz": [
    62,
    2507
  ],
  "game_0917.npz": [
    112,
    3224
  ],
  "game_0918.npz": [
    62,
    2531
  ],
  "game_0919.npz": [
    111,
    3221
  ],
  "game_0920.npz": [
    114,
    3270
  ],
  "game_0921.npz": [
    62,
    2552
  ],
  "game_0922.npz": [
    150,
    3719
  ],
  "game_0923.npz": [
    129,
    3440
  ],
  "game_0924.npz": [
    65,
    2664
  ],
  "game_0925.npz": [
    114,
    3277
  ],
  "game_0926.npz": [
    131,
    3441
  ],
  "game_0927.npz": [
    62,
    2536
  ],
  "game_0928.npz": [
    113,
    3255
  ],
  "game_0929.npz": [
    124,
    3396
  ],
  "game_0930.npz": [
    68,
    2652
  ],
  "game_0931.npz": [
    62,
    2512
  ],
  "game_0932.npz": [
    108,
    3171
  ],
  "game_0933.npz": [
    128,
    3388
  ],
  "game_0934.npz": [
    128,
    3433
  ],
  "game_0935.npz": [
    158,
    3938
  ],
  "game_0936.npz": [
    63,
    2583
  ],
  "game_0937.npz": [
    143,
    3637
  ],
  "game_0938.npz": [
    62,
    2549
  ],
  "game_0939.npz": [
    62,
    2504
  ],
  "game_0940.npz": [
    218,
    4626
  ],
  "game_0941.npz": [
    62,
    2560
  ],
  "game_0942.npz": [
    117,
    3303
  ],
  "game_0943.npz": [
    115,
    3252
  ],
  "game_0944.npz": [
    140,
    3644
  ],
  "game_0945.npz": [
    62,
    2543
  ],
  "game_0946.npz": [
    141,
    3740
  ],
  "game_0947.npz": [
    62,
    2576
  ],
  "game_0948.npz": [
    116,
    3294
  ],
  "game_0949.npz": [
    62,
    2555
  ],
  "game_0950.npz": [
    95,
    2965
  ],
  "game_0951.npz": [
    62,
    2569
  ],
  "game_0952.npz": [
    62,
    2559
  ],
  "game_0953.npz": [
    138,
    3583
  ],
  "game_0954.npz": [
    130,
    3456
  ],
  "game_0955.npz": [
    153,
    3808
  ],
  "game_0956.npz": [
    128,
    3441
  ],
  "game_0957.npz": [
    128,
    3435
  ],
  "game_0958.npz": [
    138,
    3679
  ],
  "game_0959.npz": [
    62,
    2520
  ],
  "game_0960.npz": [
    62,
    2501
  ],
  "game_0961.npz": [
    141,
    3585
  ],
  "game_0962.npz": [
    68,
    2647
  ],
  "game_0963.npz": [
    250,
    5102
  ],
  "game_0964.npz": [
    63,
    2592
  ],
  "game_0965.npz": [
    121,
    3345
  ],
  "game_0966.npz": [
    129,
    3435
  ],
  "game_0967.npz": [
    124,
    3381
  ],
  "game_0968.npz": [
    86,
    2882
  ],
  "game_0969.npz": [
    126,
    3414
  ],
  "game_0970.npz": [
    138,
    3678
  ],
  "game_0971.npz": [
    133,
    3573
  ],
  "game_0972.npz": [
    129,
    3407
  ],
  "game_0973.npz": [
    62,
    2546
  ],
  "game_0974.npz": [
    108,
    3181
  ],
  "game_0975.npz": [
    62,
    2574
  ],
  "game_0976.npz": [
    62,
    2564
  ],
  "game_0977.npz": [
    148,
    3720
  ],
  "game_0978.npz": [
    62,
    2479
  ],
  "game_0979.npz": [
    140,
    3555
  ],
  "game_0980.npz": [
    122,
    3370
  ],
  "game_0981.npz": [
    62,
    2489
  ],
  "game_0982.npz": [
    67,
    2632
  ],
  "game_0983.npz": [
    250,
    5023
  ],
  "game_0984.npz": [
    62,
    2548
  ],
  "game_0985.npz": [
    116,
    3249
  ],
  "game_0986.npz": [
    62,
    2519
  ],
  "game_0987.npz": [
    86,
    2874
  ],
  "game_0988.npz": [
    62,
    2557
  ],
  "game_0989.npz": [
    63,
    2561
  ],
  "game_0990.npz": [
    115,
    3270
  ],
  "game_0991.npz": [
    119,
    3365
  ],
  "game_0992.npz": [
    127,
    3460
  ],
  "game_0993.npz": [
    128,
    3516
  ],
  "game_0994.npz": [
    62,
    2514
  ],
  "game_0995.npz": [
    119,
    3313
  ],
  "game_0996.npz": [
    250,
    5043
  ],
  "game_0997.npz": [
    62,
    2565
  ],
  "game_0998.npz": [
    160,
    3867
  ],
  "game_0999.npz": [
    113,
    3285
  ]
}